college_football_risk/__init__.py
college_football_risk/api_client.py
college_football_risk/configuration.py
college_football_risk/exceptions.py
college_football_risk/rest.py
college_football_risk/api/__init__.py
college_football_risk/api/players_api.py
college_football_risk/api/stats_api.py
college_football_risk/api/teams_api.py
college_football_risk/api/territories_api.py
college_football_risk/models/__init__.py
college_football_risk/models/leaderboard_team.py
college_football_risk/models/player.py
college_football_risk/models/player_ratings.py
college_football_risk/models/player_stats.py
college_football_risk/models/player_team.py
college_football_risk/models/player_team_colors.py
college_football_risk/models/player_turns.py
college_football_risk/models/team.py
college_football_risk/models/team_history.py
college_football_risk/models/team_history_star_breakdown.py
college_football_risk/models/team_odds.py
college_football_risk/models/team_player.py
college_football_risk/models/team_player_last_turn.py
college_football_risk/models/team_strength.py
college_football_risk/models/team_turn_player.py
college_football_risk/models/territory.py
college_football_risk/models/territory_history.py
college_football_risk/models/territory_neighbors.py
college_football_risk/models/territory_turn.py
college_football_risk/models/territory_turn_players.py
college_football_risk/models/territory_turn_teams.py
college_football_risk/models/turn.py
college_football_risk-1.4.0.dist-info/METADATA
college_football_risk-1.4.0.dist-info/WHEEL
college_football_risk-1.4.0.dist-info/top_level.txt
college_football_risk-1.4.0.dist-info/RECORD
