Metadata-Version: 2.1
Name: college-football-risk
Version: 1.4.0
Summary: College Football Risk API
Home-page: https://github.com/bluescar/college-football-risk-python
Author: OpenAPI Generator community
Author-email: admin@collegefootballdata.com
License: UNKNOWN
Keywords: OpenAPI,OpenAPI-Generator,College Football Risk API
Platform: UNKNOWN
Requires-Dist: urllib3 (>=1.15)
Requires-Dist: six (>=1.10)
Requires-Dist: certifi
Requires-Dist: python-dateutil
